LICENSE
MANIFEST.in
README.md
pyproject.toml
setup.py
src/clusterondemandgcp/__init__.py
src/clusterondemandgcp/brightsetup.py
src/clusterondemandgcp/cli.py
src/clusterondemandgcp/clientutils.py
src/clusterondemandgcp/clustercreate.py
src/clusterondemandgcp/clusterdelete.py
src/clusterondemandgcp/clusterlist.py
src/clusterondemandgcp/clusterstart.py
src/clusterondemandgcp/clusterstop.py
src/clusterondemandgcp/configdump.py
src/clusterondemandgcp/configshow.py
src/clusterondemandgcp/configuration.py
src/clusterondemandgcp/imagelist.py
src/clusterondemandgcp/images.py
src/clusterondemandgcp/summary.py
src/cm_cluster_on_demand_gcp.egg-info/PKG-INFO
src/cm_cluster_on_demand_gcp.egg-info/SOURCES.txt
src/cm_cluster_on_demand_gcp.egg-info/dependency_links.txt
src/cm_cluster_on_demand_gcp.egg-info/entry_points.txt
src/cm_cluster_on_demand_gcp.egg-info/requires.txt
src/cm_cluster_on_demand_gcp.egg-info/top_level.txt