Metadata-Version: 2.4
Name: cm-cluster-on-demand-gcp
Version: 11.0.5
Summary: NVIDIA Base Command Manager Cluster on Demand GCP
Author-email: Base Command Manager Cloud Team <sw-bright-cloud-team@nvidia.onmicrosoft.com>
License-Expression: Apache-2.0
Project-URL: Documentation, https://docs.nvidia.com/base-command-manager/
Classifier: Development Status :: 5 - Production/Stable
Classifier: Intended Audience :: Information Technology
Classifier: Intended Audience :: Science/Research
Classifier: Intended Audience :: System Administrators
Classifier: Programming Language :: Python :: 3 :: Only
Classifier: Programming Language :: Python :: 3.12
Classifier: Topic :: System :: Clustering
Classifier: Topic :: System :: Installation/Setup
Classifier: Topic :: System :: Monitoring
Classifier: Topic :: System :: Systems Administration
Requires-Python: >=3.12
License-File: LICENSE
Requires-Dist: cm-cluster-on-demand==11.0.5
Requires-Dist: cm-cluster-on-demand-config==11.0.5
Requires-Dist: google-api-core>=2.24.2
Requires-Dist: google-cloud-asset>=3.30.1
Requires-Dist: google-cloud-compute>=1.30.0
Requires-Dist: google-cloud-filestore>=1.13.1
Requires-Dist: google-cloud-iam>=2.19.0
Requires-Dist: google-cloud-quotas>=0.1.17
Requires-Dist: google-cloud-resource-manager>=1.14.2
Requires-Dist: google-cloud-storage>=3.1.0
Requires-Dist: passlib>=1.7.4
Dynamic: license-file
Dynamic: requires-dist
